rylogic/__init__.py
rylogic/gfx/__init__.py
rylogic/gfx/colour.py
rylogic/ldraw/__init__.py
rylogic/ldraw/ldraw.py
rylogic/math/__init__.py
rylogic/math/bbox.py
rylogic/math/operations.py
rylogic/math/variable_int.py
rylogic/math/vector.py
rylogic-0.1.1.dist-info/licenses/LICENSE
rylogic-0.1.1.dist-info/METADATA
rylogic-0.1.1.dist-info/WHEEL
rylogic-0.1.1.dist-info/top_level.txt
rylogic-0.1.1.dist-info/RECORD
