Metadata-Version: 2.4
Name: rylogic
Version: 0.1.1
Summary: Python bindings for the Rylogic library
Author-email: Paul Ryland <support@rylogic.co.nz>
License-Expression: MIT
Project-URL: Homepage, https://github.com/psryland/rylogic_code
Project-URL: Bug Tracker, https://github.com/psryland/rylogic_code/issues
Keywords: rylogic,python,bindings
Classifier: Programming Language :: Python :: 3
Classifier: Operating System :: OS Independent
Requires-Python: >=3.6
License-File: LICENSE
Provides-Extra: dev
Requires-Dist: pytest; extra == "dev"
Dynamic: license-file
